markov_epidemic/__init__.py
markov_epidemic/markov_epidemic.py
markov_epidemic/seir_epidemic.py
markov_epidemic/sir_epidemic.py
markov_epidemic/sis_epidemic.py
markov_epidemic/utils.py
markov_epidemic-1.0.2.dist-info/LICENSE.txt
markov_epidemic-1.0.2.dist-info/METADATA
markov_epidemic-1.0.2.dist-info/WHEEL
markov_epidemic-1.0.2.dist-info/top_level.txt
markov_epidemic-1.0.2.dist-info/RECORD
