Metadata-Version: 2.1
Name: markov-epidemic
Version: 1.0.2
Summary: Library for stochastic simulation and study of epidemics.
Home-page: https://github.com/sauxpa/markov_epidemic
Author: Patrick Saux
Author-email: patrick.jr.saux@gmail.com
License: UNKNOWN
Platform: UNKNOWN
Requires-Python: >=3.6
Requires-Dist: numpy
Requires-Dist: networkx
